setup.cfg
setup.py
bin/striketracker
striketracker/__init__.py
striketracker.egg-info/PKG-INFO
striketracker.egg-info/SOURCES.txt
striketracker.egg-info/dependency_links.txt
striketracker.egg-info/not-zip-safe
striketracker.egg-info/requires.txt
striketracker.egg-info/top_level.txt