Metadata-Version: 1.0
Name: striketracker
Version: 0.5
Summary: Command line interface to the Highwinds CDN
Home-page: https://github.com/Highwinds/striketracker
Author: Mark Cahill
Author-email: support@highwinds.com
License: MIT
Platform: UNKNOWN
